[{"page_content": "整治重点之“驾乘机动车不系安全带”解答\n\n1、关于驾乘机动车系安全带的法律规定：《中华人民共和国道路交通安全法》第五十一条规定：机动车行驶时，驾驶人、乘坐人员应当按规定使用安全带，摩托车驾驶人及乘坐人员应当按规定戴安全头盔。也就是说，车辆行驶时，无论是前排的驾驶员，还是副驾驶室以及后排的乘客，都需要系安全带。2、关于驾驶机动车未系安全带的处罚：根据《中华人民共和国道路交通安全法》第90条、《湖北省实施中华人民共和国道路交通安全法办法》第68条第4项之规定。3、关于驾驶机动车未系安全带附加扣分的依据：根据《机动车驾驶证申领和使用规定》（公安部第139号令）附件2《道路交通安全违法行为记分分值》第四条第四项之规定：机动车驾驶人有下列违法行为之一的，一次记2分：......驾驶机动车在高速公路或者在城市快速路上行驶时，驾驶人未按规定系安全带的。4、关于机动车乘坐人员不系安全带的处罚：《湖北省实施中华人民共和国道路交通安全法办法》第六十四条之规定：行人或乘车人违反道路交通安全法律、法规有关道路通行规定的，处警告或者10元罚款；非机动车驾驶人违反道路交通安全法律、法规关于道路通行规定的，处警告或者20元罚款。5、此次治理机动车驾乘人员不系安全带违法行为的重点：公路客运、旅游客运车辆驾驶人及乘坐人不系安全带、7座以下载客汽车驾驶员及副驾驶室乘坐人员不系安全带、其他汽车驾驶员不系安全带的违法行为。", "metadata": {"url": "https://www.jingmen.gov.cn/col/col18658/index.html?kinfoGuid=181a8444-f103-4e08-955f-738c86c8ce63", "source": "json/new_json_164.json", "doc ID": 101, "filetype": "json"}}]