[{"page_content": "关于一个驾驶证一个扣分周期内处理非本人所有3辆以上不同号牌机动车违法的说明\n\n关于一个驾驶证一个扣分周期内处理非本人所有3辆以上不同号牌机动车违法的，或者一个扣分周期内3名以上驾驶人为同一号牌机动车接受违法处理的，系统将暂停其违法处理业务。对一个扣分周期内，同一驾驶人为非本人所有的3辆以上不同号牌机动车处理违法行为的情况，将纳入启动嫌疑驾驶证调查程序。现在采用的系统将自动锁定第四辆车或第四名驾驶员，交警部门会将其纳入重点人员监控并调查，调查确认其无违法嫌疑的可继续处理违法；调查确认是嫌疑人的则只能处理本人名下机动车的交通违法。", "metadata": {"url": "https://www.jingmen.gov.cn/col/col18658/index.html?kinfoGuid=8c564f89-e9d2-4a12-91c1-226d92e720c4", "source": "json/new_json_207.json", "doc ID": "149-9", "filetype": "json"}, "title": "关于一个驾驶证一个扣分周期内处理非本人所有3辆以上不同号牌机动车违法的说明"}]