[{"page_content": "通过哪些渠道可与荆楚理工学院进行招生互动咨询和信息交流？\n\n（1）荆楚理工学院招生信息网。网址：http://zsxx.jcut.edu.cn，该网站是我校发布招生政策、招生信息、进行招生咨询的官方网站。（2）QQ：1347262882。考生可随时将该号码“列为好友”，及时与我校招生咨询人员网上进行面对面的交流。（3）参加有关省级招办组织的现场招生咨询会和高中面对面招生咨询活动，各地区具体现场招生咨询会及招生咨询负责老师信息可登录我校校园招生网http://zsxx.jcut.edu.cn查询。（4）直接到我校招生办公室进行咨询或通过电话等其他方式咨询。招生办公室联系电话：0724-2355898、2355811.", "metadata": {"url": "https://www.jingmen.gov.cn/col/col18658/index.html?kinfoGuid=7f36680e-56cc-4179-8be0-3aa9dea0da64", "source": "json/new_json_21.json", "doc ID": 152, "filetype": "json"}}]