[{"page_content": "什么是低压电工证及报考流程\n\n什么是低压电工证及报考流程电工证有四证，分为特种作业操作证、电工进网作业许可证（目前已取消）、职业资格证书、建筑施工特种操作资格证。之前电工进网作业许可证下面的低压、高压、特种三个类别都已划分到电工操作证这里了。1、低压电工证怎么报考？低压电工证是安监出的，IC卡证，可通过网上和读卡器查询。一般在当地安监局报考。2、报考低压电工证需要哪些资料？一寸彩色照片3张，或提供电子版照片；身份证复印件、毕业证（或学生证）复印件各1份，或提供电子版资料，填写特种作业人员档案表一份。3、电工证在哪里复审：电工操作证也就是特种作业操作证，是卡片形式的（IC卡），这个由安监局下发，每3年复审一次。带资料去安监局办理。", "metadata": {"url": "https://www.jingmen.gov.cn/col/col18658/index.html?kinfoGuid=99a09a13-5f8f-4d29-b6bd-c539cd4517fb", "source": "json/new_json_217.json", "doc ID": "160-2", "filetype": "json"}, "title": "什么是低压电工证及报考流程"}]