[{"page_content": "为什么要重视青少年精神卫生？\n\n精神健康也称心理健康，是指个体能够恰当地评价自己、应对生活中的压力、有效率工作和学习、对家庭和社会有所贡献的一种良好状态。主要包括以下特征：智力正常；情绪稳定、心情愉快；自我意识良好；思维与行为协调统一；人际关系融洽；适应能力良好。青少年的心理活动是活跃而波动的阶段，是精神卫生保健最关键时刻。由于青少年期处于发育前后时期，内分泌生理改变突出、植物神经不稳定、情绪易波动。这个时期易受家庭、学校、和社会不良环境的影响，可出现放荡、出走、流浪、饮酒、吸烟、斗殴、行凶、欺骗和色情行为等。也易患精神分裂症、神经症等", "metadata": {"url": "https://www.jingmen.gov.cn/col/col18658/index.html?kinfoGuid=cf2853c1-9168-4580-b6f3-9961e6e42ae0", "source": "json/new_json_228.json", "doc ID": "172-11", "filetype": "json"}, "title": "为什么要重视青少年精神卫生？"}]