[{"page_content": "想要申报雨露计划补助，应当具备哪些条件？\n\n2021年11月12日，湖北省乡村振兴局印发的《关于做好过渡期内雨露计划工作的通知》的规定，申报雨露计划补助的对象，应当具备下列条件：1.雨露计划职业教育补助对象为全国防返贫监测信息系统中已脱贫家庭子女(含监测帮扶对象家庭)；2.正在接受中高等职业教育(含普通中专、职业高中、技工学校、普通大专、高职院校、技师学院)；3.申报对象是取得正式全日制学籍的在校生(含在校期间顶岗实习)。　　需特别注意：对监测对象尚未消除风险的，纳入雨露计划政策补助范围；边缘易致贫户和突发严重困难户(脱贫户除外)按程序消除风险后，从下一学期起停止发放补助。", "metadata": {"url": "https://www.jingmen.gov.cn/col/col18658/index.html?kinfoGuid=3b40d799-5bc2-429a-a151-c75bbdec5b18", "source": "json/new_json_260.json", "doc ID": "208-16", "filetype": "json"}, "title": "想要申报雨露计划补助，应当具备哪些条件？"}]