[{"page_content": "市农产品质量检验所农产品质量检验服务指南\n\n一、适用范围：本服务指南适用于办理农产品质量检验业务二、基础要素（一）事项名称：农产品、原粮及油料、食用植物油、畜禽产品等质量检验（二）申请形式：窗口申请（三）受理机构：荆门市农产品质量检验所业务技术室地址：荆门市掇刀区兴隆大道227号承办人员：雷彬办公室电话：0724-6661022手机：13872938818（四）实施机构：荆门市农产品质量检验所（五）法律依据：1.《中华人民共和国农产品质量安全法》2.《中华人民共和国食品安全法》3.《粮食质量监管实施办法》(试行)（六）职能：从事农产品、原粮及油料、食用植物油、畜禽产品等质量检验检测工作。（七）受理要求1.受理条件（1）营业执照（2）委托检验单（3）标准资料（八）办结时限：是否受理检验1个工作日内回复，农产品、原粮及油料中单个样品定量检验7个工作日；原粮及油料、食用植物油单个样品理化指标检验3个工作日；畜禽产品单个样品定量检验7个工作日。多批次样品检验与客户协商完成时限。（九）申请材料：农产品检验申请材料1.营业执照，复印件1份；2.检验委托单，窗口领取，填写完整，纸质版原件1份；3.质量标准，纸质版原件1份；4.其他要求：真实，合法，完整。（十）结果名称：1.检验报告书（十一）收费:本事项不收费（十二）办理时间:法定工作日上午8:30-12:00下午14:30-18:00（夏季上午8:30-12:00下午15:00-18:00以市政府通知为准）（十三）办事流程办事流程:1.申请申请人通过办理窗口进行申请。2.受理对申请人提交的申请资料进行审核，资料齐全并在检测资质范围内，予以受理；材料不齐全或不符合要求的，告知申请人补正；不在检测资质范围内的，不予受理。3.检验根据检验协议书和国家相关标准、规范要求进行检验。4.报告出具检验报告经编制、审核、签发后出具，报告完成。5.报告领取申请人按检验协议书确定的时间和方式领取检验报告。", "metadata": {"url": "https://www.jingmen.gov.cn/col/col18658/index.html?kinfoGuid=7c129ad1-754e-4c80-9606-a59594930cfb", "source": "json/new_json_293.json", "doc ID": 244, "filetype": "json"}}]