[{"page_content": "京山市城乡居民购房补贴申领办理程序是什么？\n\n(一)申请。符合享受购房补贴的居民可以在缴纳契税后，携带以下资料向市行政服务中心二楼市房屋交易管理所网签备案窗口申领补贴。申领事项需申请人本人办理，非本人申请的需持公证委托书委托办理。1.《京山市非中心城区户籍人员购房补贴申请表》一式四份（见附件网上下载，网址：http://www.jingshan.gov.cn/art/2022/2/21/art_2030_867700.html（或登陆京山人民政府官网首页政府信息公开法定主动公开内容公共资源配置保障性住房，对应文件下载附件申请表）2.婚姻证明复印件（核原件）和户口簿(提交申请前到户籍所在地公安部门进行更新，复印本人页和全家人页)等家庭关系材料；3.本人身份证复印件（核原件，身份证正面、反面、银行卡正面复印在同一页纸上）及银行账号（京山市内农商行一类银行卡号）；4.契税完税凭证复印件（核原件）。（二）审查。行政服务中心一楼市公安局窗口对申请人户籍信息进行查询，行政服务中心二楼市不动产登记部门查询申请人住房登记信息，行政服务中心二楼市房屋交易管理所对商品房买卖合同网签信息进行查询。市房屋交易管理所对申请人的资料进行初审后，于每月15日前将初审合格的购房补贴资料送交市财政部门审核确认。（三）发放。市财政部门自审核确认之日起3个月内将补贴资金支付至申领对象银行账户。", "metadata": {"url": "https://www.jingmen.gov.cn/col/col18658/index.html?kinfoGuid=32d57fd8-ce61-4ab9-9a11-761f4e529983", "source": "json/new_json_49.json", "doc ID": 277, "filetype": "json"}}]