[{"page_content": "H7N9病例主要临床表现有哪些？\n\nH7N9病例的潜伏期一般多为7天以内，也可长达10天。肺炎为主要临床表现，患者常出现发热、咳嗽、咳痰，可伴有头痛、肌肉酸痛、腹泻或呕吐等症状。重症患者病情发展迅速，多在发病3-7天出现重症肺炎，体温大多持续在39℃以上，出现呼吸困难，可伴有咯血痰。常快速进展为急性呼吸窘迫综合征、脓毒性休克和多脏器功能障碍综合征。少数患者可为轻症，仅表现为发热伴上呼吸道感染症状。H7N9病例早期发病无特异性表现，早诊早治困难，后期重症病例治疗效果差，病死率高，目前报告病例的总体病死率在40%左右。", "metadata": {"url": "https://www.jingmen.gov.cn/col/col18658/index.html?kinfoGuid=5d7d04b9-b412-4692-b649-df7acc4a6e58", "source": "json/new_json_101.json", "doc ID": 32, "filetype": "json"}, "title": "H7N9病例主要临床表现有哪些？"}]