[{"page_content": "荆门城区公交IC卡充值站点有哪些？\n\n1、掇刀区公交IC卡营业厅（荆门市掇刀区虎牙关大道46号）电话：6036334；2．东宝区公交IC卡营业厅（荆门市东宝区金龙泉大道1号，火车站对面）电话：2387058；3.公交IC卡海慧充值点（海慧车站旁）；4.公交IC卡金城充值点（实验小学对面）；5.花园小区充值点（花园小区站务亭）；6.城南新区充值点（城南新区菜场斜对面，话机世界移动手机营业厅内）；7.洪源充值点（洪源市场对面金城超市内总服务台）；8.白石坡充值点（掇刀石小学对面公交站台）；9.政务中心充值点（新政务中心主楼大厅）；10.荆门公交驻残联服务点（荆门市东宝区象山二路12号，荆门市残联）；市民在上述站点办理公交业务过程中，如遇服务和咨询问题，可拨打市公交服务投诉电话2449922。", "metadata": {"url": "https://www.jingmen.gov.cn/col/col18658/index.html?kinfoGuid=b6ad1f51-e4f5-4c5e-8209-9e1bb1850fcc", "source": "json/new_json_114.json", "doc ID": 46, "filetype": "json"}}]